causalspyne/README.md
causalspyne/__init__.py
causalspyne/ancestral_acc.py
causalspyne/ancestral_shd.py
causalspyne/conf.py
causalspyne/dag2ancestral.py
causalspyne/dag_gen.py
causalspyne/dag_interface.py
causalspyne/dag_manipulator.py
causalspyne/dag_stack_indexer.py
causalspyne/dag_viewer.py
causalspyne/data_gen.py
causalspyne/dataset.py
causalspyne/draw_dags.py
causalspyne/edge_models.py
causalspyne/erdo_renyi_plp.py
causalspyne/gen_dag_2level.py
causalspyne/implicit_gen_Sigma.py
causalspyne/implicit_omega.py
causalspyne/implicit_omega_condition_on_w.py
causalspyne/implicit_spectrum_histogram.py
causalspyne/is_dag.py
causalspyne/main.py
causalspyne/noise_idiosyncratic.py
causalspyne/poset_approach.py
causalspyne/py3_9_10_compatibility.py
causalspyne/utils_causallearn_g2ancestral.py
causalspyne/utils_closure.py
causalspyne/utils_cov_precision.py
causalspyne/utils_topological_sort.py
causalspyne/weight.py
causalspyne/wishart.py
causalspyne-0.1.6.dist-info/METADATA
causalspyne-0.1.6.dist-info/WHEEL
causalspyne-0.1.6.dist-info/RECORD
