Metadata-Version: 2.4
Name: causalspyne
Version: 0.1.6
Summary: hierarchical data generation for causal discovery and abstraction
Requires-Python: >=3.12
Requires-Dist: causal-learn>=0.1.4.3
Requires-Dist: matplotlib>=3.10.7
Requires-Dist: networkx>=3.5
Requires-Dist: numpy>=2.3.4
Requires-Dist: pandas>=2.3.3
Requires-Dist: scipy>=1.16.2
